llama_agents/__init__.py
llama_agents/app/__init__.py
llama_agents/app/app.py
llama_agents/app/components/__init__.py
llama_agents/app/components/human_list.py
llama_agents/app/components/service_list.py
llama_agents/app/components/task_list.py
llama_agents/app/components/types.py
llama_agents/cli/__init__.py
llama_agents/cli/command_line.py
llama_agents/client/__init__.py
llama_agents/client/async_client.py
llama_agents/client/sync_client.py
llama_agents/control_plane/__init__.py
llama_agents/control_plane/base.py
llama_agents/control_plane/server.py
llama_agents/launchers/__init__.py
llama_agents/launchers/local.py
llama_agents/launchers/server.py
llama_agents/message_consumers/__init__.py
llama_agents/message_consumers/base.py
llama_agents/message_consumers/callable.py
llama_agents/message_consumers/remote.py
llama_agents/message_publishers/__init__.py
llama_agents/message_publishers/publisher.py
llama_agents/message_queues/__init__.py
llama_agents/message_queues/apache_kafka.py
llama_agents/message_queues/base.py
llama_agents/message_queues/rabbitmq.py
llama_agents/message_queues/redis.py
llama_agents/message_queues/simple.py
llama_agents/messages/__init__.py
llama_agents/messages/base.py
llama_agents/orchestrators/__init__.py
llama_agents/orchestrators/agent.py
llama_agents/orchestrators/base.py
llama_agents/orchestrators/orchestrator_router.py
llama_agents/orchestrators/pipeline.py
llama_agents/services/__init__.py
llama_agents/services/agent.py
llama_agents/services/base.py
llama_agents/services/component.py
llama_agents/services/human.py
llama_agents/services/tool.py
llama_agents/services/types.py
llama_agents/tools/__init__.py
llama_agents/tools/agent_service_tool.py
llama_agents/tools/meta_service_tool.py
llama_agents/tools/service_as_tool.py
llama_agents/tools/service_component.py
llama_agents/tools/service_tool.py
llama_agents/tools/utils.py
llama_agents/types.py
llama_agents/utils.py
llama_agents-0.0.14.dist-info/LICENSE
llama_agents-0.0.14.dist-info/METADATA
llama_agents-0.0.14.dist-info/WHEEL
llama_agents-0.0.14.dist-info/entry_points.txt
llama_agents-0.0.14.dist-info/RECORD
