Metadata-Version: 2.1
Name: llama-agents
Version: 0.0.14
Summary: 
Author: Logan Markewich
Author-email: logan.markewich@live.com
Maintainer: Logan Markewich
Maintainer-email: logan@llamaindex.ai
Requires-Python: >=3.8.1,<4.0
Classifier: Programming Language :: Python :: 3
Classifier: Programming Language :: Python :: 3.9
Classifier: Programming Language :: Python :: 3.10
Classifier: Programming Language :: Python :: 3.11
Classifier: Programming Language :: Python :: 3.12
Provides-Extra: kafka
Provides-Extra: rabbitmq
Provides-Extra: redis
Requires-Dist: aio-pika (>=9.4.2,<10.0.0) ; extra == "rabbitmq"
Requires-Dist: aiokafka (>=0.11.0,<0.12.0) ; extra == "kafka"
Requires-Dist: fastapi (>=0.109.1,<0.110.0)
Requires-Dist: kafka-python-ng (>=2.2.2,<3.0.0) ; extra == "kafka"
Requires-Dist: llama-index-core (>=0.10.50,<0.11.0)
Requires-Dist: pytest-asyncio (>=0.23.7,<0.24.0)
Requires-Dist: pytest-mock (>=3.14.0,<4.0.0)
Requires-Dist: redis (>=5.0.7,<6.0.0) ; extra == "redis"
Requires-Dist: textual (>=0.70.0,<0.71.0)
Requires-Dist: uvicorn (>=0.30.1,<0.31.0)
